pyramid_zodbconn/__init__.py
pyramid_zodbconn/compat.py
pyramid_zodbconn/tests/__init__.py
pyramid_zodbconn/tests/test_init.py
pyramid_zodbconn-0.8.1.dist-info/DESCRIPTION.rst
pyramid_zodbconn-0.8.1.dist-info/METADATA
pyramid_zodbconn-0.8.1.dist-info/RECORD
pyramid_zodbconn-0.8.1.dist-info/WHEEL
pyramid_zodbconn-0.8.1.dist-info/metadata.json
pyramid_zodbconn-0.8.1.dist-info/top_level.txt
